{ "backgroundcolor":"#cccccc",
 "height":7,
 "layers":[
        {
         "height":7,
         "name":"boundary",
         "objects":[
                {
                 "height":900,
                 "name":"",
                 "properties":
                    {

                    },
                 "type":"boundary",
                 "visible":true,
                 "width":1000,
                 "x":0,
                 "y":0
                }],
         "opacity":1,
         "type":"objectgroup",
         "visible":false,
         "width":10,
         "x":0,
         "y":0
        }, 
        {
         "height":7,
         "name":"sprites",
         "objects":[
                {
                 "height":350,
                 "name":"",
                 "properties":
                    {
                     "layer":"background",
                     "repeatV":"false",
                     "texture":"stars_texture.png",
                     "translation":"{0.01,0.01}",
                     "zorder":"backgroundTexture"
                    },
                 "type":"scrollingTexture",
                 "visible":true,
                 "width":1000,
                 "x":0,
                 "y":0
                }, 
                {
                 "height":100,
                 "name":"",
                 "properties":
                    {
                     "anchor":"{0,1}",
                     "flip":"{true,false}",
                     "frame":"grass_2.png",
                     "zorder":"grass"
                    },
                 "type":"sprite",
                 "visible":true,
                 "width":200,
                 "x":100,
                 "y":200
                }, 
                {
                 "height":100,
                 "name":"",
                 "properties":
                    {
                     "anchor":"{0,1}",
                     "frame":"grass_2.png",
                     "zorder":"grass"
                    },
                 "type":"sprite",
                 "visible":true,
                 "width":200,
                 "x":300,
                 "y":200
                }, 
                {
                 "height":100,
                 "name":"",
                 "properties":
                    {
                     "anchor":"{0,1}",
                     "frame":"grass_2.png",
                     "zorder":"grass"
                    },
                 "type":"sprite",
                 "visible":true,
                 "width":200,
                 "x":-100,
                 "y":200
                }, 
                {
                 "height":100,
                 "name":"",
                 "properties":
                    {
                     "anchor":"{0.5,0}",
                     "frame":"mount_2.png"
                    },
                 "type":"dancingSprite",
                 "visible":true,
                 "width":100,
                 "x":800,
                 "y":600
                }, 
                {
                 "height":100,
                 "name":"",
                 "properties":
                    {
                     "anchor":"{0.5,0}",
                     "frame":"mount_3.png"
                    },
                 "type":"dancingSprite",
                 "visible":true,
                 "width":100,
                 "x":200,
                 "y":600
                }, 
                {
                 "height":100,
                 "name":"",
                 "properties":
                    {
                     "anchor":"{0.5,0}",
                     "frame":"mount_1.png"
                    },
                 "type":"dancingSprite",
                 "visible":true,
                 "width":100,
                 "x":200,
                 "y":200
                }, 
                {
                 "height":0,
                 "name":"",
                 "polygon":[
                        {
                         "x":98,
                         "y":-423
                        }, 
                        {
                         "x":398,
                         "y":-423
                        }, 
                        {
                         "x":198,
                         "y":-23
                        }, 
                        {
                         "x":98,
                         "y":-23
                        }],
                 "properties":
                    {
                     "color":"{100,100,100}",
                     "layer":"background",
                     "texture":"ground_texture.png"
                    },
                 "type":"texture",
                 "visible":true,
                 "width":0,
                 "x":2,
                 "y":723
                }, 
                {
                 "height":0,
                 "name":"",
                 "polygon":[
                        {
                         "x":205,
                         "y":-468
                        }, 
                        {
                         "x":205,
                         "y":-68
                        }, 
                        {
                         "x":5,
                         "y":-68
                        }],
                 "properties":
                    {
                     "color":"{180,180,180}",
                     "layer":"background",
                     "texture":"ground_texture.png"
                    },
                 "type":"texture",
                 "visible":true,
                 "width":0,
                 "x":195,
                 "y":768
                }],
         "opacity":1,
         "type":"objectgroup",
         "visible":true,
         "width":10,
         "x":0,
         "y":0
        }, 
        {
         "height":7,
         "name":"physics",
         "objects":[
                {
                 "height":100,
                 "name":"",
                 "properties":
                    {

                    },
                 "type":"player",
                 "visible":true,
                 "width":100,
                 "x":0,
                 "y":200
                }, 
                {
                 "height":100,
                 "name":"",
                 "properties":
                    {
                     "frame":"cake.png",
                     "path":"path2"
                    },
                 "type":"target",
                 "visible":true,
                 "width":100,
                 "x":600,
                 "y":600
                }, 
                {
                 "height":100,
                 "name":"",
                 "properties":
                    {
                     "frame":"cupcake.png",
                     "path":"path2"
                    },
                 "type":"coin",
                 "visible":true,
                 "width":100,
                 "x":600,
                 "y":450
                }, 
                {
                 "height":100,
                 "name":"",
                 "properties":
                    {
                     "frame":"cupcake.png",
                     "path":"path1"
                    },
                 "type":"coin",
                 "visible":true,
                 "width":100,
                 "x":400,
                 "y":375
                }, 
                {
                 "height":100,
                 "name":"",
                 "properties":
                    {
                     "frame":"cupcake.png",
                     "path":"path1"
                    },
                 "type":"coin",
                 "visible":true,
                 "width":100,
                 "x":400,
                 "y":525
                }, 
                {
                 "height":0,
                 "name":"path1",
                 "polyline":[
                        {
                         "x":100,
                         "y":0
                        }, 
                        {
                         "x":400,
                         "y":0
                        }, 
                        {
                         "x":100,
                         "y":0
                        }],
                 "properties":
                    {
                     "action":"moveTo",
                     "loop":"true",
                     "speed":"0.3"
                    },
                 "type":"path",
                 "visible":true,
                 "width":0,
                 "x":300,
                 "y":400
                }, 
                {
                 "height":0,
                 "name":"path2",
                 "polyline":[
                        {
                         "x":300,
                         "y":100
                        }, 
                        {
                         "x":0,
                         "y":100
                        }, 
                        {
                         "x":300,
                         "y":100
                        }],
                 "properties":
                    {
                     "action":"moveTo",
                     "loop":"true",
                     "speed":"0.3"
                    },
                 "type":"path",
                 "visible":true,
                 "width":0,
                 "x":400,
                 "y":400
                }, 
                {
                 "height":100,
                 "name":"",
                 "properties":
                    {
                     "frame":"bad1.png",
                     "path":"pathBad"
                    },
                 "type":"bad",
                 "visible":true,
                 "width":100,
                 "x":600,
                 "y":600
                }, 
                {
                 "height":0,
                 "name":"pathBad",
                 "polyline":[
                        {
                         "x":500,
                         "y":300
                        }, 
                        {
                         "x":300,
                         "y":300
                        }, 
                        {
                         "x":300,
                         "y":-100
                        }, 
                        {
                         "x":500,
                         "y":-100
                        }, 
                        {
                         "x":300,
                         "y":-100
                        }, 
                        {
                         "x":300,
                         "y":300
                        }, 
                        {
                         "x":500,
                         "y":300
                        }],
                 "properties":
                    {
                     "action":"moveTo",
                     "loop":"true",
                     "speed":"0.3"
                    },
                 "type":"path",
                 "visible":true,
                 "width":0,
                 "x":500,
                 "y":400
                }, 
                {
                 "height":75,
                 "name":"",
                 "properties":
                    {

                    },
                 "type":"ground",
                 "visible":true,
                 "width":500,
                 "x":0,
                 "y":300
                }],
         "opacity":1,
         "type":"objectgroup",
         "visible":true,
         "width":10,
         "x":0,
         "y":0
        }],
 "orientation":"orthogonal",
 "properties":
    {
     "backgroundSprite":"season1_background.png",
     "batch":"{'rainbow.png', 'balloon_rope.png'}",
     "defaultColor":"{255,133,135,255}",
     "ground_color":"",
     "ground_opacity":"",
     "ground_texture":"ground_texture.png",
     "level":"6",
     "particleBatch":"{'star_particle_2.png'}",
     "season":"1",
     "spritesheets":"{'actions01.plist','actions02.plist'}",
     "tip":"",
     "tool":"",
     "tool_blink":"rope",
     "tool_block":"0",
     "tool_rope":"1"
    },
 "tileheight":100,
 "tilesets":[],
 "tilewidth":100,
 "version":1,
 "width":10
}
